ora2pg/__init__.py
ora2pg/gen_pg_tabs.py
ora2pg/ora2pg.py
ora2pg/pg2ora.py
ora2pg-1.0.6.dist-info/METADATA
ora2pg-1.0.6.dist-info/WHEEL
ora2pg-1.0.6.dist-info/entry_points.txt
ora2pg-1.0.6.dist-info/top_level.txt
ora2pg-1.0.6.dist-info/RECORD
