Metadata-Version: 2.1
Name: ora2pg
Version: 1.0.6
Summary: Oracle to postgresql migration tool
Home-page: https://github.com/romkoval/py-ora2pg
Author: Roman Kovalev
Author-email: romkoval@gmail.com
License: UNKNOWN
Project-URL: Bug Tracker, https://github.com/romkoval/py-ora2pg/issues
Platform: UNKNOWN
Classifier: Programming Language :: Python :: 3
Classifier: License :: OSI Approved :: MIT License
Classifier: Operating System :: OS Independent
Requires-Python: >=3.6
Requires-Dist: cx-Oracle (==7.0.0)
Requires-Dist: py-postgresql (==1.2.1)
Requires-Dist: tqdm (==4.28.1)
